CHANGES.txt
MANIFEST.in
README.txt
setup.py
src/djangorecipe/__init__.py
src/djangorecipe/boilerplate.py
src/djangorecipe/fcgi.py
src/djangorecipe/manage.py
src/djangorecipe/recipe.py
src/djangorecipe/test.py
src/djangorecipe/tests.py
src/djangorecipe/wsgi.py
src/redsolution.djangorecipe.egg-info/PKG-INFO
src/redsolution.djangorecipe.egg-info/SOURCES.txt
src/redsolution.djangorecipe.egg-info/dependency_links.txt
src/redsolution.djangorecipe.egg-info/entry_points.txt
src/redsolution.djangorecipe.egg-info/not-zip-safe
src/redsolution.djangorecipe.egg-info/requires.txt
src/redsolution.djangorecipe.egg-info/top_level.txt