Metadata-Version: 1.0
Name: redsolution.djangorecipe
Version: 1.1.2
Summary: Buildout recipe for Django
Home-page: https://github.com/rvanlaar/djangorecipe
Author: Roland van Laar
Author-email: roland@micite.net
License: BSD
Platform: UNKNOWN
Classifier: Framework :: Buildout
Classifier: Framework :: Django
Classifier: Topic :: Software Development :: Build Tools
Classifier: Development Status :: 5 - Production/Stable
Classifier: License :: OSI Approved :: BSD License
Classifier: Programming Language :: Python :: 2.5
Classifier: Programming Language :: Python :: 2.6
Classifier: Programming Language :: Python :: 2.7
Classifier: Programming Language :: Python :: 3
